bitbucket_linter.py
bitbucket_linter-0.1.6.dist-info/DESCRIPTION.rst
bitbucket_linter-0.1.6.dist-info/METADATA
bitbucket_linter-0.1.6.dist-info/RECORD
bitbucket_linter-0.1.6.dist-info/WHEEL
bitbucket_linter-0.1.6.dist-info/entry_points.txt
bitbucket_linter-0.1.6.dist-info/metadata.json
bitbucket_linter-0.1.6.dist-info/top_level.txt
